brain_segmen/__init__.py
brain_segmen/segmen.py
brain_segmen-0.0.2.dist-info/LICENSE
brain_segmen-0.0.2.dist-info/METADATA
brain_segmen-0.0.2.dist-info/WHEEL
brain_segmen-0.0.2.dist-info/top_level.txt
brain_segmen-0.0.2.dist-info/RECORD
