Metadata-Version: 2.1
Name: brain-segmen
Version: 0.0.2
Summary: Berikut ini adalah deskripsi singkat bagaimana segmentasi otak dibuat
Home-page: https://github.com/asyrofist/Brain-Segmentation
Author: Asyrofi (Rakha Asyrofi)
Author-email: rakhasyrofist@gmail.com
License: UNKNOWN
Project-URL: Bug Tracker, https://github.com/asyrofist/Brain-Segmentation/issues
Platform: UNKNOWN
Classifier: Programming Language :: Python :: 3
Classifier: License :: OSI Approved :: MIT License
Classifier: Operating System :: OS Independent
Requires-Python: >=3.6
License-File: LICENSE
